ironic_python_agent_builder/__init__.py
ironic_python_agent_builder-7.0.0.data/data/share/ironic-python-agent-builder/dib/burn-in/README.rst
ironic_python_agent_builder-7.0.0.data/data/share/ironic-python-agent-builder/dib/burn-in/element-deps
ironic_python_agent_builder-7.0.0.data/data/share/ironic-python-agent-builder/dib/burn-in/package-installs.yaml
ironic_python_agent_builder-7.0.0.data/data/share/ironic-python-agent-builder/dib/element/ironic-python-agent-podman/README.rst
ironic_python_agent_builder-7.0.0.data/data/share/ironic-python-agent-builder/dib/element/ironic-python-agent-podman/element-deps
ironic_python_agent_builder-7.0.0.data/data/share/ironic-python-agent-builder/dib/element/ironic-python-agent-podman/package-installs.yaml
ironic_python_agent_builder-7.0.0.data/data/share/ironic-python-agent-builder/dib/element/ironic-python-agent-podman/environment.d/10-setup.bash
ironic_python_agent_builder-7.0.0.data/data/share/ironic-python-agent-builder/dib/element/ironic-python-agent-podman/pre-finalise.d/10-ipa-podman-config
ironic_python_agent_builder-7.0.0.data/data/share/ironic-python-agent-builder/dib/element/ironic-python-agent-podman/pre-finalise.d/20-ipa-config
ironic_python_agent_builder-7.0.0.data/data/share/ironic-python-agent-builder/dib/element/ironic-python-agent-podman/pre-finalise.d/30-ipa-steps
ironic_python_agent_builder-7.0.0.data/data/share/ironic-python-agent-builder/dib/extra-hardware/README.rst
ironic_python_agent_builder-7.0.0.data/data/share/ironic-python-agent-builder/dib/extra-hardware/element-deps
ironic_python_agent_builder-7.0.0.data/data/share/ironic-python-agent-builder/dib/extra-hardware/package-installs.yaml
ironic_python_agent_builder-7.0.0.data/data/share/ironic-python-agent-builder/dib/extra-hardware/pkg-map
ironic_python_agent_builder-7.0.0.data/data/share/ironic-python-agent-builder/dib/extra-hardware/environment.d/10-enable-rdo-deps.bash
ironic_python_agent_builder-7.0.0.dist-info/licenses/AUTHORS
ironic_python_agent_builder-7.0.0.dist-info/licenses/LICENSE
ironic_python_agent_builder-7.0.0.dist-info/METADATA
ironic_python_agent_builder-7.0.0.dist-info/WHEEL
ironic_python_agent_builder-7.0.0.dist-info/entry_points.txt
ironic_python_agent_builder-7.0.0.dist-info/pbr.json
ironic_python_agent_builder-7.0.0.dist-info/top_level.txt
ironic_python_agent_builder-7.0.0.dist-info/RECORD
