Metadata-Version: 2.4
Name: ironic-python-agent-builder
Version: 7.0.0
Summary: Tools and scripts to build Ironic Python Agent
Home-page: https://docs.openstack.org/ironic-python-agent-builder/latest/
Author: OpenStack
Author-email: openstack-discuss@lists.openstack.org
Classifier: Environment :: OpenStack
Classifier: Intended Audience :: Information Technology
Classifier: Intended Audience :: System Administrators
Classifier: License :: OSI Approved :: Apache Software License
Classifier: Operating System :: POSIX :: Linux
License-File: LICENSE
License-File: AUTHORS
Requires-Dist: diskimage-builder>=3.4.0
Dynamic: author
Dynamic: author-email
Dynamic: classifier
Dynamic: description
Dynamic: home-page
Dynamic: license-file
Dynamic: requires-dist
Dynamic: summary
